{"tradeDate":"20260107","totals":{"month":"-","monthID":"-","globex":"173,424","openOutcry":"0","totalVolume":"175,714","blockVolume":"469","efpVol":"1,521","efrVol":"0","eooVol":"0","efsVol":"0","subVol":"0","pntVol":"2,290","tasVol":"2,851","deliveries":"150","opnt":"-","aon":"-","atClose":"154,284","change":"1,044","strike":"-","exercises":"0"},"monthData":[{"month":"JAN 2026","monthID":"JAN-2026-Calls","globex":"2,093","openOutcry":"0","totalVolume":"2,093","blockVolume":"0","efpVol":"0","efrVol":"0","eooVol":"0","efsVol":"0","subVol":"0","pntVol":"0","tasVol":"0","deliveries":"150","opnt":"-","aon":"-","atClose":"2,155","change":"1,431","strike":"0","exercises":"0"},{"month":"FEB 2026","monthID":"FEB-2026-Calls","globex":"4,558","openOutcry":"0","totalVolume":"4,558","blockVolume":"0","efpVol":"0","efrVol":"0","eooVol":"0","efsVol":"0","subVol":"0","pntVol":"0","tasVol":"0","deliveries":"0","opnt":"-","aon":"-","atClose":"3,423","change":"1,564","strike":"0","exercises":"0"},{"month":"MAR 2026","monthID":"MAR-2026-Calls","globex":"150,619","openOutcry":"0","totalVolume":"152,706","blockVolume":"291","efpVol":"1,496","efrVol":"0","eooVol":"0","efsVol":"0","subVol":"0","pntVol":"2,087","tasVol":"2,484","deliveries":"0","opnt":"-","aon":"-","atClose":"104,574","change":"-3,052","strike":"0","exercises":"0"},{"month":"APR 2026","monthID":"APR-2026-Calls","globex":"431","openOutcry":"0","totalVolume":"431","blockVolume":"0","efpVol":"0","efrVol":"0","eooVol":"0","efsVol":"0","subVol":"0","pntVol":"0","tasVol":"0","deliveries":"0","opnt":"-","aon":"-","atClose":"195","change":"2","strike":"0","exercises":"0"},{"month":"MAY 2026","monthID":"MAY-2026-Calls","globex":"10,587","openOutcry":"0","totalVolume":"10,719","blockVolume":"107","efpVol":"25","efrVol":"0","eooVol":"0","efsVol":"0","subVol":"0","pntVol":"132","tasVol":"232","deliveries":"0","opnt":"-","aon":"-","atClose":"21,185","change":"765","strike":"0","exercises":"0"},{"month":"JUN 2026","monthID":"JUN-2026-Calls","globex":"43","openOutcry":"0","totalVolume":"43","blockVolume":"0","efpVol":"0","efrVol":"0","eooVol":"0","efsVol":"0","subVol":"0","pntVol":"0","tasVol":"0","deliveries":"0","opnt":"-","aon":"-","atClose":"86","change":"1","strike":"0","exercises":"0"},{"month":"JUL 2026","monthID":"JUL-2026-Calls","globex":"2,864","openOutcry":"0","totalVolume":"2,935","blockVolume":"71","efpVol":"0","efrVol":"0","eooVol":"0","efsVol":"0","subVol":"0","pntVol":"71","tasVol":"88","deliveries":"0","opnt":"-","aon":"-","atClose":"14,062","change":"121","strike":"0","exercises":"0"},{"month":"AUG 2026","monthID":"AUG-2026-Calls","globex":"11","openOutcry":"0","totalVolume":"11","blockVolume":"0","efpVol":"0","efrVol":"0","eooVol":"0","efsVol":"0","subVol":"0","pntVol":"0","tasVol":"0","deliveries":"0","opnt":"-","aon":"-","atClose":"13","change":"0","strike":"0","exercises":"0"},{"month":"SEP 2026","monthID":"SEP-2026-Calls","globex":"1,175","openOutcry":"0","totalVolume":"1,175","blockVolume":"0","efpVol":"0","efrVol":"0","eooVol":"0","efsVol":"0","subVol":"0","pntVol":"0","tasVol":"47","deliveries":"0","opnt":"-","aon":"-","atClose":"3,435","change":"59","strike":"0","exercises":"0"},{"month":"OCT 2026","monthID":"OCT-2026-Calls","globex":"0","openOutcry":"0","totalVolume":"0","blockVolume":"0","efpVol":"0","efrVol":"0","eooVol":"0","efsVol":"0","subVol":"0","pntVol":"0","tasVol":"0","deliveries":"0","opnt":"-","aon":"-","atClose":"11","change":"0","strike":"0","exercises":"0"},{"month":"NOV 2026","monthID":"NOV-2026-Calls","globex":"8","openOutcry":"0","totalVolume":"8","blockVolume":"0","efpVol":"0","efrVol":"0","eooVol":"0","efsVol":"0","subVol":"0","pntVol":"0","tasVol":"0","deliveries":"0","opnt":"-","aon":"-","atClose":"15","change":"1","strike":"0","exercises":"0"},{"month":"DEC 2026","monthID":"DEC-2026-Calls","globex":"855","openOutcry":"0","totalVolume":"855","blockVolume":"0","efpVol":"0","efrVol":"0","eooVol":"0","efsVol":"0","subVol":"0","pntVol":"0","tasVol":"0","deliveries":"0","opnt":"-","aon":"-","atClose":"4,695","change":"143","strike":"0","exercises":"0"},{"month":"JAN 2027","monthID":"JAN-2027-Calls","globex":"0","openOutcry":"0","totalVolume":"0","blockVolume":"0","efpVol":"0","efrVol":"0","eooVol":"0","efsVol":"0","subVol":"0","pntVol":"0","tasVol":"0","deliveries":"0","opnt":"-","aon":"-","atClose":"13","change":"0","strike":"0","exercises":"0"},{"month":"FEB 2027","monthID":"FEB-2027-Calls","globex":"0","openOutcry":"0","totalVolume":"0","blockVolume":"0","efpVol":"0","efrVol":"0","eooVol":"0","efsVol":"0","subVol":"0","pntVol":"0","tasVol":"0","deliveries":"0","opnt":"-","aon":"-","atClose":"3","change":"0","strike":"0","exercises":"0"},{"month":"MAR 2027","monthID":"MAR-2027-Calls","globex":"120","openOutcry":"0","totalVolume":"120","blockVolume":"0","efpVol":"0","efrVol":"0","eooVol":"0","efsVol":"0","subVol":"0","pntVol":"0","tasVol":"0","deliveries":"0","opnt":"-","aon":"-","atClose":"196","change":"9","strike":"0","exercises":"0"},{"month":"APR 2027","monthID":"APR-2027-Calls","globex":"0","openOutcry":"0","totalVolume":"0","blockVolume":"0","efpVol":"0","efrVol":"0","eooVol":"0","efsVol":"0","subVol":"0","pntVol":"0","tasVol":"0","deliveries":"0","opnt":"-","aon":"-","atClose":"1","change":"0","strike":"0","exercises":"0"},{"month":"MAY 2027","monthID":"MAY-2027-Calls","globex":"32","openOutcry":"0","totalVolume":"32","blockVolume":"0","efpVol":"0","efrVol":"0","eooVol":"0","efsVol":"0","subVol":"0","pntVol":"0","tasVol":"0","deliveries":"0","opnt":"-","aon":"-","atClose":"50","change":"-1","strike":"0","exercises":"0"},{"month":"JUL 2027","monthID":"JUL-2027-Calls","globex":"5","openOutcry":"0","totalVolume":"5","blockVolume":"0","efpVol":"0","efrVol":"0","eooVol":"0","efsVol":"0","subVol":"0","pntVol":"0","tasVol":"0","deliveries":"0","opnt":"-","aon":"-","atClose":"22","change":"-1","strike":"0","exercises":"0"},{"month":"SEP 2027","monthID":"SEP-2027-Calls","globex":"8","openOutcry":"0","totalVolume":"8","blockVolume":"0","efpVol":"0","efrVol":"0","eooVol":"0","efsVol":"0","subVol":"0","pntVol":"0","tasVol":"0","deliveries":"0","opnt":"-","aon":"-","atClose":"40","change":"-2","strike":"0","exercises":"0"},{"month":"DEC 2027","monthID":"DEC-2027-Calls","globex":"15","openOutcry":"0","totalVolume":"15","blockVolume":"0","efpVol":"0","efrVol":"0","eooVol":"0","efsVol":"0","subVol":"0","pntVol":"0","tasVol":"0","deliveries":"0","opnt":"-","aon":"-","atClose":"60","change":"4","strike":"0","exercises":"0"},{"month":"JUL 2028","monthID":"JUL-2028-Calls","globex":"0","openOutcry":"0","totalVolume":"0","blockVolume":"0","efpVol":"0","efrVol":"0","eooVol":"0","efsVol":"0","subVol":"0","pntVol":"0","tasVol":"0","deliveries":"0","opnt":"-","aon":"-","atClose":"34","change":"0","strike":"0","exercises":"0"},{"month":"DEC 2028","monthID":"DEC-2028-Calls","globex":"0","openOutcry":"0","totalVolume":"0","blockVolume":"0","efpVol":"0","efrVol":"0","eooVol":"0","efsVol":"0","subVol":"0","pntVol":"0","tasVol":"0","deliveries":"0","opnt":"-","aon":"-","atClose":"16","change":"0","strike":"0","exercises":"0"}],"updateTime":"2026-01-08T15:00:10.000Z","empty":false}
